circlify.py
circlify-0.15.1.dist-info/licenses/LICENSE
circlify-0.15.1.dist-info/METADATA
circlify-0.15.1.dist-info/WHEEL
circlify-0.15.1.dist-info/top_level.txt
circlify-0.15.1.dist-info/RECORD
