Metadata-Version: 2.4
Name: circlify
Version: 0.15.1
Summary: Circle packing algorithm for Python
Author-email: Elmotec <elmotec@gmx.com>
License: MIT
Project-URL: Homepage, http://github.com/elmotec/circlify
Project-URL: Repository, http://github.com/elmotec/circlify
Keywords: circle,packing,enclosure,hierarchy,graph,display,visualization
Classifier: Development Status :: 4 - Beta
Classifier: Operating System :: OS Independent
Classifier: Natural Language :: English
Classifier: Programming Language :: Python :: 3.9
Classifier: Programming Language :: Python :: 3.10
Classifier: Programming Language :: Python :: 3.11
Classifier: Programming Language :: Python :: 3.12
Classifier: Programming Language :: Python :: 3.13
Classifier: Topic :: Software Development
Classifier: Topic :: Utilities
Classifier: Topic :: Scientific/Engineering :: Visualization
Classifier: Intended Audience :: Developers
Requires-Python: >=3.9
License-File: LICENSE
Provides-Extra: test
Requires-Dist: coverage>=5.3; extra == "test"
Requires-Dist: coveralls>=3.3.1; extra == "test"
Requires-Dist: ruff>=0.1.0; extra == "test"
Requires-Dist: hypothesis>=6.50.1; extra == "test"
Provides-Extra: develop
Requires-Dist: coverage>=5.3; extra == "develop"
Requires-Dist: coveralls>=3.3.1; extra == "develop"
Requires-Dist: ruff>=0.1.0; extra == "develop"
Requires-Dist: hypothesis>=6.50.1; extra == "develop"
Requires-Dist: commitizen>=2.28.0; extra == "develop"
Requires-Dist: matplotlib>=3.5.2; extra == "develop"
Requires-Dist: pre-commit>=2.19.0; extra == "develop"
Requires-Dist: wheel>=0.37.1; extra == "develop"
Dynamic: license-file
